jobbatch/__init__.py
jobbatch/main.py
jobbatch-1.0.5.dist-info/entry_points.txt
jobbatch-1.0.5.dist-info/LICENSE
jobbatch-1.0.5.dist-info/WHEEL
jobbatch-1.0.5.dist-info/METADATA
jobbatch-1.0.5.dist-info/RECORD
