Metadata-Version: 2.1
Name: jobbatch
Version: 1.0.5
Summary: A utility for splitting tasks up into batches
Author: Quentin Stafford-Fraser
Author-email: quentin@pobox.com
Requires-Python: >=3.5
Classifier: Programming Language :: Python :: 3
Classifier: Programming Language :: Python :: 3.10
Classifier: Programming Language :: Python :: 3.5
Classifier: Programming Language :: Python :: 3.6
Classifier: Programming Language :: Python :: 3.7
Classifier: Programming Language :: Python :: 3.8
Classifier: Programming Language :: Python :: 3.9
